p4tools/__init__.py
p4tools/_modidx.py
p4tools/data_extract.py
p4tools/io.py
p4tools/markings.py
p4tools/plotting.py
p4tools-0.13.3.dist-info/licenses/LICENSE
p4tools-0.13.3.dist-info/METADATA
p4tools-0.13.3.dist-info/WHEEL
p4tools-0.13.3.dist-info/entry_points.txt
p4tools-0.13.3.dist-info/top_level.txt
p4tools-0.13.3.dist-info/RECORD
