Metadata-Version: 2.4
Name: p4tools
Version: 0.13.3
Summary: Tools for working with data from the Planet Four Zooniverse project.
Home-page: https://github.com/michaelaye/p4tools
Author: Michael Aye
Author-email: kmichael.aye@gmail.com
License: MIT License
Project-URL: Documentation, https://michaelaye.github.io/p4tools/
Keywords: zooniverse citizen_science panoptes
Classifier: Development Status :: 4 - Beta
Classifier: Intended Audience :: Developers
Classifier: Natural Language :: English
Classifier: Programming Language :: Python :: 3.10
Classifier: Programming Language :: Python :: 3.12
Classifier: Programming Language :: Python :: 3.13
Classifier: License :: OSI Approved :: MIT License
Requires-Python: >=3.10
License-File: LICENSE
Requires-Dist: packaging
Requires-Dist: pandas
Requires-Dist: pooch
Requires-Dist: numpy
Requires-Dist: matplotlib
Requires-Dist: shapely
Requires-Dist: tqdm
Requires-Dist: pyarrow
Provides-Extra: dev
Dynamic: author
Dynamic: author-email
Dynamic: classifier
Dynamic: description
Dynamic: description-content-type
Dynamic: home-page
Dynamic: keywords
Dynamic: license
Dynamic: license-file
Dynamic: project-url
Dynamic: provides-extra
Dynamic: requires-dist
Dynamic: requires-python
Dynamic: summary
